LICENSE
simple_downloader/__init__.py
simple_downloader-0.1.2.dist-info/LICENSE
simple_downloader-0.1.2.dist-info/WHEEL
simple_downloader-0.1.2.dist-info/METADATA
simple_downloader-0.1.2.dist-info/RECORD
